robot_eval_logger/__init__.py
robot_eval_logger/eval_logger.py
robot_eval_logger/utils.py
robot_eval_logger/storage/__init__.py
robot_eval_logger/storage/base_saver.py
robot_eval_logger/storage/hugging_face.py
robot_eval_logger/storage/local.py
robot_eval_logger/typing/__init__.py
robot_eval_logger/typing/eval_metadata.py
robot_eval_logger/typing/traj_data.py
robot_eval_logger/visualize/__init__.py
robot_eval_logger/visualize/visualize_frames.py
robot_eval_logger/visualize/wandb.py
robot_eval_logger-0.0.1.dist-info/licenses/LICENSE
robot_eval_logger-0.0.1.dist-info/METADATA
robot_eval_logger-0.0.1.dist-info/WHEEL
robot_eval_logger-0.0.1.dist-info/entry_points.txt
robot_eval_logger-0.0.1.dist-info/top_level.txt
robot_eval_logger-0.0.1.dist-info/RECORD
