Metadata-Version: 2.4
Name: robot_eval_logger
Version: 0.0.1
Summary: A flexible logger for robot evaluations with visualization and data storage capabilities
Author-email: Paul Zhou <zhouzypaul@gmail.com>
Maintainer-email: Paul Zhou <zhouzypaul@gmail.com>
License: MIT
Project-URL: Homepage, https://github.com/zhouzypaul/robot_eval_logger
Project-URL: Repository, https://github.com/zhouzypaul/robot_eval_logger
Project-URL: Documentation, https://github.com/zhouzypaul/robot_eval_logger#readme
Project-URL: Bug Tracker, https://github.com/zhouzypaul/robot_eval_logger/issues
Keywords: robotics,evaluation,logging,visualization,wandb,huggingface
Classifier: Development Status :: 3 - Alpha
Classifier: Intended Audience :: Developers
Classifier: Intended Audience :: Science/Research
Classifier: License :: OSI Approved :: MIT License
Classifier: Operating System :: OS Independent
Classifier: Programming Language :: Python :: 3
Classifier: Programming Language :: Python :: 3.8
Classifier: Programming Language :: Python :: 3.9
Classifier: Programming Language :: Python :: 3.10
Classifier: Programming Language :: Python :: 3.11
Classifier: Topic :: Scientific/Engineering :: Artificial Intelligence
Classifier: Topic :: Software Development :: Libraries :: Python Modules
Requires-Python: >=3.8
License-File: LICENSE
Requires-Dist: absl-py
Requires-Dist: wandb
Requires-Dist: moviepy==1.0.3
Requires-Dist: huggingface-hub
Requires-Dist: numpy<2.0.0
Provides-Extra: dev
Requires-Dist: pre-commit; extra == "dev"
Requires-Dist: black; extra == "dev"
Requires-Dist: flake8; extra == "dev"
Requires-Dist: pytest; extra == "dev"
Requires-Dist: pytest-cov; extra == "dev"
Dynamic: license-file
